piskg/__init__.py
piskg/__main__.py
piskg-0.2018.8.14.1618.dist-info/METADATA
piskg-0.2018.8.14.1618.dist-info/RECORD
piskg-0.2018.8.14.1618.dist-info/WHEEL
piskg-0.2018.8.14.1618.dist-info/entry_points.txt
piskg-0.2018.8.14.1618.dist-info/top_level.txt
