Metadata-Version: 2.1
Name: piskg
Version: 0.2018.8.14.1618
Summary: Python IPFS Swarm Key Generator
Home-page: https://github.com/machawk1/piskg
Author: Mat Kelly
Author-email: mkelly@cs.odu.edu
License: MIT
Download-URL: https://github.com/machawk1/piskg
Keywords: ipfs keygen
Platform: UNKNOWN
Classifier: License :: OSI Approved :: MIT License
Classifier: Programming Language :: Python :: 2
Classifier: Programming Language :: Python :: 2.7
Classifier: Programming Language :: Python :: 3
Classifier: Programming Language :: Python :: 3.7
Classifier: Topic :: Security :: Cryptography
Classifier: Topic :: System :: Distributed Computing
Classifier: Topic :: Utilities
Provides: piskg
